{
  "project_info": {
    "project_number": "330098937290",
    "project_id": "learnmovies-acd8b",
    "storage_bucket": "learnmovies-acd8b.firebasestorage.app"
  },
  "client": [
    {
      "client_info": {
        "mobilesdk_app_id": "1:330098937290:android:2c46a00454c4e468d59333",
        "android_client_info": {
          "package_name": "org.example.project"
        }
      },
      "oauth_client": [],
      "api_key": [
        {
          "current_key": "AIzaSyCZ4ao7k2OVRBy2gncYFtMciD3ZQUhmzgE"
        }
      ],
      "services": {
        "appinvite_service": {
          "other_platform_oauth_client": []
        }
      }
    }
  ],
  "configuration_version": "1"
}